CHANGES.txt
LICENSE
MANIFEST.in
README.rst
setup.py
dotted/__init__.py
dotted/collection.py
dotted/utils.py
dotted.egg-info/PKG-INFO
dotted.egg-info/SOURCES.txt
dotted.egg-info/dependency_links.txt
dotted.egg-info/requires.txt
dotted.egg-info/top_level.txt
dotted/test/__init__.py
dotted/test/test_collection.py