Metadata-Version: 1.1
Name: dotted
Version: 0.1.2
Summary: Access dicts and lists with a dotted path notation.
Home-page: https://github.com/carlosescri/DottedDict
Author: Carlos Escribano Rey
Author-email: carlos@nettoys.es
License: The MIT License (MIT)
